{
    "swagger": "2.0",
    "info": {
        "description": "This is a National ID API Documentation.",
        "title": "National ID API",
        "termsOfService": "http://swagger.io/terms/",
        "contact": {
            "name": "API Support",
            "url": "http://ramyadmz.github.io/CV/",
            "email": "ramyadmz@gmail.com"
        },
        "license": {
            "name": "Apache 2.0",
            "url": "http://www.apache.org/licenses/LICENSE-2.0.html"
        },
        "version": "1.0"
    },
    "host": "petstore.swagger.io",
    "basePath": "/v2",
    "paths": {
        "/ID/validation/{id}": {
            "get": {
                "description": "check id validation and return city information",
                "consumes": [
                    "application/json"
                ],
                "produces": [
                    "text/html"
                ],
                "tags": [
                    "ID"
                ],
                "summary": "check id number",
                "operationId": "check-id",
                "parameters": [
                    {
                        "type": "string",
                        "description": "id",
                        "name": "id",
                        "in": "path",
                        "required": true
                    }
                ]
            }
        }
    }
}